balanna/__init__.py
balanna/display_scenes.py
balanna/trimesh.py
balanna/utils/__init__.py
balanna/utils/geometry.py
balanna-0.1.2.dist-info/LICENSE
balanna-0.1.2.dist-info/METADATA
balanna-0.1.2.dist-info/WHEEL
balanna-0.1.2.dist-info/top_level.txt
balanna-0.1.2.dist-info/RECORD
